streamlit-speed-dial/__init__.py
streamlit-speed-dial/frontend/build/asset-manifest.json
streamlit-speed-dial/frontend/build/bootstrap.min.css
streamlit-speed-dial/frontend/build/index.html
streamlit-speed-dial/frontend/build/static/js/main.d3903c78.js
streamlit-speed-dial/frontend/build/static/js/main.d3903c78.js.LICENSE.txt
streamlit-speed-dial/frontend/build/static/js/main.d3903c78.js.map
streamlit_speed_dial/__init__.py
streamlit_speed_dial/frontend/build/asset-manifest.json
streamlit_speed_dial/frontend/build/bootstrap.min.css
streamlit_speed_dial/frontend/build/index.html
streamlit_speed_dial/frontend/build/static/js/main.5bb3bc6b.js
streamlit_speed_dial/frontend/build/static/js/main.5bb3bc6b.js.LICENSE.txt
streamlit_speed_dial/frontend/build/static/js/main.5bb3bc6b.js.map
streamlit_speed_dial/frontend/build/static/js/main.d3903c78.js
streamlit_speed_dial/frontend/build/static/js/main.d3903c78.js.LICENSE.txt
streamlit_speed_dial/frontend/build/static/js/main.d3903c78.js.map
streamlit_speed_dial-0.0.3.dist-info/LICENSE
streamlit_speed_dial-0.0.3.dist-info/METADATA
streamlit_speed_dial-0.0.3.dist-info/WHEEL
streamlit_speed_dial-0.0.3.dist-info/top_level.txt
streamlit_speed_dial-0.0.3.dist-info/RECORD
