Metadata-Version: 2.1
Name: streamlit-speed-dial
Version: 0.0.3
Summary: Streamlit component that allows you to make speed dial 
Home-page: https://github.com/BlueGob/streamlit-speed-dial
Author: Moslem gannoun
Author-email: moslemgannoun@gmail.com
License: UNKNOWN
Platform: UNKNOWN
Requires-Python: >=3.7
License-File: LICENSE
Requires-Dist: streamlit >=0.63
